{"is_source_file": true, "format": "Python", "description": "This file contains Pydantic schema models for the Notes API, including data structures for creating, updating, and representing notes, along with validation logic and a factory function for creating new notes.", "external_files": ["pydantic", "datetime", "typing", "uuid"], "external_methods": ["pydantic.BaseModel", "pydantic.Field", "pydantic.field_validator", "uuid.uuid4", "datetime.utcnow"], "published": ["Note", "NoteBase", "NoteCreate", "NoteUpdate", "new_note_from_create"], "classes": [{"name": "NoteBase", "description": "Base schema with shared attributes for note creation and update operations, including validation for title and content."}, {"name": "NoteCreate", "description": "Schema for creating a new note, inherits basic attributes from NoteBase."}, {"name": "NoteUpdate", "description": "Schema for partially updating an existing note, with optional fields and validation."}, {"name": "Note", "description": "Schema representing a persisted note, including identifiers and timestamps."}], "methods": [{"name": "str title_trim_and_validate(cls, v: str)", "description": "Validator that trims whitespace and ensures the title is not empty for create/update.", "scope": "NoteBase", "scopeKind": "class"}, {"name": "str content_sanitize(cls, v: str)", "description": "Sanitizes the content by trimming trailing whitespace.", "scope": "NoteBase", "scopeKind": "class"}, {"name": "Optional[str] title_optional_trim_and_validate(cls, v: Optional[str])", "description": "Validator for optional title updates, trims and validates if provided.", "scope": "NoteUpdate", "scopeKind": "class"}, {"name": "Optional[str] content_optional_trim(cls, v: Optional[str])", "description": "Sanitizes optional content by trimming trailing whitespace if provided.", "scope": "NoteUpdate", "scopeKind": "class"}, {"name": "Note new_note_from_create(payload: NoteCreate)", "description": "Factory function to generate a new Note instance from a NoteCreate payload, assigning UUID and timestamps.", "scope": "", "scopeKind": ""}], "calls": ["datetime.utcnow", "uuid.uuid4"], "search-terms": ["pydantic schemas", "NoteCreate", "field_validator", "UUID", "UTC timestamps"], "state": 2, "file_id": 6, "knowledge_revision": 22, "git_revision": "", "revision_history": [{"13": ""}, {"22": ""}], "ctags": [{"_type": "tag", "name": "Note", "path": "/home/kavia/workspace/code-generation/simple-notes-app-278505-278530/notes_backend/src/api/schemas.py", "pattern": "/^class Note(NoteBase):$/", "language": "Python", "kind": "class"}, {"_type": "tag", "name": "NoteBase", "path": "/home/kavia/workspace/code-generation/simple-notes-app-278505-278530/notes_backend/src/api/schemas.py", "pattern": "/^class NoteBase(BaseModel):$/", "language": "Python", "kind": "class"}, {"_type": "tag", "name": "NoteCreate", "path": "/home/kavia/workspace/code-generation/simple-notes-app-278505-278530/notes_backend/src/api/schemas.py", "pattern": "/^class NoteCreate(NoteBase):$/", "language": "Python", "kind": "class"}, {"_type": "tag", "name": "NoteUpdate", "path": "/home/kavia/workspace/code-generation/simple-notes-app-278505-278530/notes_backend/src/api/schemas.py", "pattern": "/^class NoteUpdate(BaseModel):$/", "language": "Python", "kind": "class"}, {"_type": "tag", "name": "content", "path": "/home/kavia/workspace/code-generation/simple-notes-app-278505-278530/notes_backend/src/api/schemas.py", "pattern": "/^    content: Optional[str] = Field(None, max_length=10000, description=\"Updated content\")$/", "language": "Python", "typeref": "typename:Optional[str]", "kind": "variable", "scope": "NoteUpdate", "scopeKind": "class"}, {"_type": "tag", "name": "content", "path": "/home/kavia/workspace/code-generation/simple-notes-app-278505-278530/notes_backend/src/api/schemas.py", "pattern": "/^    content: str = Field($/", "language": "Python", "typeref": "typename:str", "kind": "variable", "scope": "NoteBase", "scopeKind": "class"}, {"_type": "tag", "name": "content_optional_trim", "path": "/home/kavia/workspace/code-generation/simple-notes-app-278505-278530/notes_backend/src/api/schemas.py", "pattern": "/^    def content_optional_trim(cls, v: Optional[str]) -> Optional[str]:$/", "language": "Python", "typeref": "typename:Optional[str]", "kind": "member", "signature": "(cls, v: Optional[str])", "scope": "NoteUpdate", "scopeKind": "class"}, {"_type": "tag", "name": "content_sanitize", "path": "/home/kavia/workspace/code-generation/simple-notes-app-278505-278530/notes_backend/src/api/schemas.py", "pattern": "/^    def content_sanitize(cls, v: str) -> str:$/", "language": "Python", "typeref": "typename:str", "kind": "member", "signature": "(cls, v: str)", "scope": "NoteBase", "scopeKind": "class"}, {"_type": "tag", "name": "created_at", "path": "/home/kavia/workspace/code-generation/simple-notes-app-278505-278530/notes_backend/src/api/schemas.py", "pattern": "/^    created_at: datetime = Field(..., description=\"Creation timestamp (UTC)\")$/", "language": "Python", "typeref": "typename:datetime", "kind": "variable", "scope": "Note", "scopeKind": "class"}, {"_type": "tag", "name": "id", "path": "/home/kavia/workspace/code-generation/simple-notes-app-278505-278530/notes_backend/src/api/schemas.py", "pattern": "/^    id: UUID = Field(..., description=\"Unique identifier for the note\")$/", "language": "Python", "typeref": "typename:UUID", "kind": "variable", "scope": "Note", "scopeKind": "class"}, {"_type": "tag", "name": "model_config", "path": "/home/kavia/workspace/code-generation/simple-notes-app-278505-278530/notes_backend/src/api/schemas.py", "pattern": "/^    model_config = {$/", "language": "Python", "kind": "variable", "scope": "Note", "scopeKind": "class"}, {"_type": "tag", "name": "new_note_from_create", "path": "/home/kavia/workspace/code-generation/simple-notes-app-278505-278530/notes_backend/src/api/schemas.py", "pattern": "/^def new_note_from_create(payload: NoteCreate) -> Note:$/", "language": "Python", "typeref": "typename:Note", "kind": "function", "signature": "(payload: NoteCreate)"}, {"_type": "tag", "name": "title", "path": "/home/kavia/workspace/code-generation/simple-notes-app-278505-278530/notes_backend/src/api/schemas.py", "pattern": "/^    title: Optional[str] = Field(None, min_length=1, max_length=200, description=\"Updated title\"/", "language": "Python", "typeref": "typename:Optional[str]", "kind": "variable", "scope": "NoteUpdate", "scopeKind": "class"}, {"_type": "tag", "name": "title", "path": "/home/kavia/workspace/code-generation/simple-notes-app-278505-278530/notes_backend/src/api/schemas.py", "pattern": "/^    title: str = Field(..., min_length=1, max_length=200, description=\"Title of the note\")$/", "language": "Python", "typeref": "typename:str", "kind": "variable", "scope": "NoteBase", "scopeKind": "class"}, {"_type": "tag", "name": "title_optional_trim_and_validate", "path": "/home/kavia/workspace/code-generation/simple-notes-app-278505-278530/notes_backend/src/api/schemas.py", "pattern": "/^    def title_optional_trim_and_validate(cls, v: Optional[str]) -> Optional[str]:$/", "language": "Python", "typeref": "typename:Optional[str]", "kind": "member", "signature": "(cls, v: Optional[str])", "scope": "NoteUpdate", "scopeKind": "class"}, {"_type": "tag", "name": "title_trim_and_validate", "path": "/home/kavia/workspace/code-generation/simple-notes-app-278505-278530/notes_backend/src/api/schemas.py", "pattern": "/^    def title_trim_and_validate(cls, v: str) -> str:$/", "language": "Python", "typeref": "typename:str", "kind": "member", "signature": "(cls, v: str)", "scope": "NoteBase", "scopeKind": "class"}, {"_type": "tag", "name": "updated_at", "path": "/home/kavia/workspace/code-generation/simple-notes-app-278505-278530/notes_backend/src/api/schemas.py", "pattern": "/^    updated_at: datetime = Field(..., description=\"Last update timestamp (UTC)\")$/", "language": "Python", "typeref": "typename:datetime", "kind": "variable", "scope": "Note", "scopeKind": "class"}], "hash": "69c3971819a603a9cc46d3b087fbbadb", "format-version": 4, "code-base-name": "notes_backend", "filename": "notes_backend/src/api/schemas.py", "fields": [{"name": "Optional[str] content", "scope": "NoteUpdate", "scopeKind": "class", "description": "unavailable"}, {"name": "str content", "scope": "NoteBase", "scopeKind": "class", "description": "unavailable"}, {"name": "datetime created_at", "scope": "Note", "scopeKind": "class", "description": "unavailable"}, {"name": "UUID id", "scope": "Note", "scopeKind": "class", "description": "unavailable"}, {"name": "model_config = {", "scope": "Note", "scopeKind": "class", "description": "unavailable"}, {"name": "Optional[str] title", "scope": "NoteUpdate", "scopeKind": "class", "description": "unavailable"}, {"name": "str title", "scope": "NoteBase", "scopeKind": "class", "description": "unavailable"}, {"name": "datetime updated_at", "scope": "Note", "scopeKind": "class", "description": "unavailable"}]}